setup.cfg
setup.py
coinop/__init__.py
coinop/ecdsa_pure.py
coinop/keys.py
coinop/multiwallet.py
coinop/passphrasebox.py
coinop/script.py
coinop/transaction.py
coinop/util.py
coinop.egg-info/PKG-INFO
coinop.egg-info/SOURCES.txt
coinop.egg-info/dependency_links.txt
coinop.egg-info/not-zip-safe
coinop.egg-info/pbr.json
coinop.egg-info/requires.txt
coinop.egg-info/top_level.txt
coinop/bit/__init__.py
coinop/crypto/__init__.py
coinop/crypto/passphrasebox.py
coinop/test/__init__.py
coinop/test/test_passphrase_box.py