Metadata-Version: 1.0
Name: coinop
Version: 0.3.1
Summary: Crypto-currency conveniences
Home-page: http://github.com/GemHQ/coinop-py
Author: Matt Smith
Author-email: matt@gem.co
License: MIT
Platform: UNKNOWN
